protocookie/__init__.py
protocookie/config.json
protocookie/protocookie.proto
protocookie/protocookie.py
protocookie/protocookie_pb2.py
protocookie/server.py
protocookie-0.0.1.dist-info/LICENCE
protocookie-0.0.1.dist-info/METADATA
protocookie-0.0.1.dist-info/WHEEL
protocookie-0.0.1.dist-info/top_level.txt
protocookie-0.0.1.dist-info/RECORD
