Metadata-Version: 2.1
Name: protocookie
Version: 0.0.1
Summary: Proof of Concept for storing data in Fernet encrypted protobuffed cookies
Home-page: https://github.com/fordindin/protocookie
Author: Denis Barov
Author-email: dindin@dindin.ru
License: UNKNOWN
Platform: UNKNOWN
Classifier: Programming Language :: Python :: 3
Classifier: License :: OSI Approved :: MIT License
Classifier: Operating System :: OS Independent
Requires-Dist: protobuf
Requires-Dist: flask
Requires-Dist: cryptography
